django_notebook_config/__init__.py
django_notebook_config/main.py
tests/__init__.py
tests/test_import.py
django_notebook_config-0.1.1.dist-info/LICENSE
django_notebook_config-0.1.1.dist-info/METADATA
django_notebook_config-0.1.1.dist-info/WHEEL
django_notebook_config-0.1.1.dist-info/top_level.txt
django_notebook_config-0.1.1.dist-info/RECORD
