Metadata-Version: 2.1
Name: django-notebook-config
Version: 0.1.1
Summary: A utility to easily use Django in IDEs Jupyter Notebooks.
Home-page: https://github.com/WazedKhan/django-notebook-config
Author: Abdul Wajed Khan
Author-email: wajed.abdul.khan@gmail.com
License: MIT
Keywords: django jupyter notebook development helper debugger
Classifier: Programming Language :: Python :: 3
Classifier: License :: OSI Approved :: MIT License
Classifier: Operating System :: OS Independent
Classifier: Framework :: Django
Classifier: Intended Audience :: Developers
Requires-Python: >=3.6
License-File: LICENSE
